nodebuilder/__init__.py
nodebuilder/cli.py
nodebuilder/core/__init__.py
nodebuilder/core/add_node.py
nodebuilder/core/add_workflow.py
nodebuilder/core/compose.py
nodebuilder/core/fetch.py
nodebuilder/core/list_items.py
nodebuilder/core/mcp.py
nodebuilder/templates/nodes/summarizer/node.py
nodebuilder/templates/nodes/translator/node.py
nodebuilder/templates/workflows/summarize_and_translate/workflow.py
nodebuilder-1.0.0.dist-info/licenses/LICENSE
nodebuilder-1.0.0.dist-info/METADATA
nodebuilder-1.0.0.dist-info/WHEEL
nodebuilder-1.0.0.dist-info/entry_points.txt
nodebuilder-1.0.0.dist-info/top_level.txt
nodebuilder-1.0.0.dist-info/RECORD
