Metadata-Version: 2.4
Name: nodebuilder
Version: 1.0.0
Summary: Shadcn-style CLI to copy LangGraph nodes and workflows into your project.
Author-email: Your Name <you@example.com>
License: MIT
Requires-Python: >=3.9
License-File: LICENSE
Requires-Dist: typer>=0.9.0
Requires-Dist: requests>=2.25.0
Dynamic: license-file
